nd_sdk/__init__.py
nd_sdk/auto_init.py
nd_sdk/caching/__init__.py
nd_sdk/caching/base.py
nd_sdk/caching/factory.py
nd_sdk/caching/in_memory_cache.py
nd_sdk/caching/redis_cache.py
nd_sdk/cli/__init__.py
nd_sdk/cli/main.py
nd_sdk/cli/validators.py
nd_sdk/cli/generators/__init__.py
nd_sdk/cli/generators/base.py
nd_sdk/cli/generators/microservice.py
nd_sdk/cli/templates/__init__.py
nd_sdk/cli/templates/microservice/Dockerfile.j2
nd_sdk/cli/templates/microservice/Readme.md.j2
nd_sdk/cli/templates/microservice/config.yaml.j2
nd_sdk/cli/templates/microservice/config_loader.py.j2
nd_sdk/cli/templates/microservice/dependencies.py.j2
nd_sdk/cli/templates/microservice/endpoint.py.j2
nd_sdk/cli/templates/microservice/endpoints_init.py.j2
nd_sdk/cli/templates/microservice/main.py.j2
nd_sdk/cli/templates/microservice/model.py.j2
nd_sdk/cli/templates/microservice/models_init.py.j2
nd_sdk/cli/templates/microservice/service.py.j2
nd_sdk/cli/templates/microservice/service_base.py.j2
nd_sdk/cli/templates/microservice/settings.py.j2
nd_sdk/config/__init__.py
nd_sdk/config/data_config.py
nd_sdk/config/factory.py
nd_sdk/config/loaders.py
nd_sdk/config/settings.py
nd_sdk/exception_handler/__init__.py
nd_sdk/exception_handler/factory.py
nd_sdk/exception_handler/exception/__init__.py
nd_sdk/exception_handler/exception/base_exceptions.py
nd_sdk/exception_handler/exception/idp_exceptions.py
nd_sdk/observability/__init__.py
nd_sdk/observability/context_manager.py
nd_sdk/observability/factory.py
nd_sdk/observability/otel_exporter.py
nd_sdk/observability/logging/__init__.py
nd_sdk/observability/logging/azure_app_insights_logger.py
nd_sdk/observability/logging/base.py
nd_sdk/observability/logging/cloudwatch_logger.py
nd_sdk/observability/logging/otel_logger.py
nd_sdk/observability/logging/std_logger.py
nd_sdk/observability/metrics/__init__.py
nd_sdk/observability/metrics/base.py
nd_sdk/observability/metrics/otel_metrics.py
nd_sdk/observability/tracing/__init__.py
nd_sdk-1.3.0.dist-info/METADATA
nd_sdk-1.3.0.dist-info/WHEEL
nd_sdk-1.3.0.dist-info/entry_points.txt
nd_sdk-1.3.0.dist-info/top_level.txt
nd_sdk-1.3.0.dist-info/RECORD
