Metadata-Version: 2.1
Name: nd-sdk
Version: 1.3.0
Summary: Unified SDK for Observability, Caching and Storage
Author: Jeyesh Vishnu
Author-email: jeyesh.vishnu@novacisdigital.com
Requires-Python: >=3.8
Requires-Dist: azure-storage-blob ~=12.16.0
Requires-Dist: azure-core ~=1.29.5
Requires-Dist: Flask ~=2.1.2
Requires-Dist: redis ~=6.1.1
Requires-Dist: Werkzeug ~=2.2.2
Requires-Dist: opentelemetry-api >=1.20.0
Requires-Dist: opentelemetry-sdk >=1.20.0
Requires-Dist: opentelemetry-exporter-otlp-proto-http >=1.20.0
Requires-Dist: aiohttp >=3.8.0
Requires-Dist: click >=8.0.0
Requires-Dist: pyyaml >=6.0
Requires-Dist: jinja2 >=3.0.0
Requires-Dist: pydantic >=2.0.0
Requires-Dist: azure-monitor-opentelemetry ~=1.6.12
